myinput/__init__.py
myinput-0.1.2.dist-info/METADATA
myinput-0.1.2.dist-info/WHEEL
myinput-0.1.2.dist-info/top_level.txt
myinput-0.1.2.dist-info/RECORD
